pythonanywhere_test_package/__init__.py
pythonanywhere_test_package-0.0.1.dist-info/METADATA
pythonanywhere_test_package-0.0.1.dist-info/RECORD
pythonanywhere_test_package-0.0.1.dist-info/WHEEL
pythonanywhere_test_package-0.0.1.dist-info/top_level.txt
