Metadata-Version: 2.1
Name: pythonanywhere-test-package
Version: 0.0.1
Summary: A package for testing
Home-page: https://github.com/pythonanywhere/pythonanywhere_test_package
Author: PythonAnywhere Developers
Author-email: developers@pythonanywhere.com
License: UNKNOWN
Platform: UNKNOWN
Classifier: Programming Language :: Python :: 2
Classifier: Programming Language :: Python :: 3
Classifier: License :: OSI Approved :: MIT License
Classifier: Operating System :: OS Independent
